[
  {
    "name": "Google Chrome",
    "url": "https://dl.google.com/tag/s/appguid%3D{8A69D345-D564-463C-AFF1-A69D9E530F96}%26iid%3D{50883C9D-6549-A3DA-3C1F-AEB15B8A98DE}%26lang%3Den%26browser%3D5%26usagestats%3D1%26appname%3DGoogle%2520Chrome%26needsadmin%3Dprefers%26ap%3Dx64-stable-statsdef_1%26brand%3DVDKB%26installdataindex%3Dempty/update2/installers/ChromeSetup.exe"
  },
  {
    "name": "Firefox",
    "url": "https://cdn.stubdownloader.services.mozilla.com/builds/firefox-stub/en-US/win/5bd9569abdcaaa46dde94a6a58af26a81de05c50ca099ae0c37081f8f8c11804/Firefox Installer.exe"
  },
  {
    "name": "Opera",
    "url": "https://net.geo.opera.com/opera/stable/windows?utm_source=bing&utm_medium=ba_ose&utm_campaign=Worldwide%2B-%2BBrand%2B-%2BEN&utm_content=Branded%2B-%2BExact&http_referrer=https%3A%2F%2Fwww.opera.com%2F%3Futm_source%3Dbing%26utm_medium%3Dpa%26utm_campaign%3DWorldwide%2520-%2520Brand%2520-%2520EN%26msclkid%3D79aac6d95c901652d231a33354b4d9f4%26utm_term%3DOpera%26utm_content%3DBranded%2520-%2520Exact&utm_site=opera_com&utm_lastpage=opera.com%2F&dl_token=99052403"
  },
  {
    "name": "Spotify",
    "url": "https://download.scdn.co/SpotifySetup.exe"
  },
  {
    "name": "1Password",
    "url": "https://downloads.1password.com/win/1PasswordSetup-latest.exe"
  },
  {
    "name": "Slack",
    "url": "https://downloads.slack-edge.com/releases/windows/4.36.140/prod/x64/SlackSetup.exe"
  },
  {
    "name": "Zoom",
    "url": "https://cdn.zoom.us/prod/5.17.10.33775/ZoomInstaller.exe"
  },
  {
    "name": "Notion",
    "url": "https://desktop-release.notion-static.com/Notion Setup 3.2.1.exe"
  },
  {
    "name": "VLC",
    "url": "https://edgeuno-bog2.mm.fcix.net/videolan-ftp/vlc/3.0.20/win32/vlc-3.0.20-win32.exe"
  },
  {
    "name": "Git",
    "url": "https://objects.githubusercontent.com/github-production-release-asset-2e65be/23216272/2d1c35e2-ece0-4287-bc51-b221f43922b4?X-Amz-Algorithm=AWS4-HMAC-SHA256&X-Amz-Credential=AKIAVCODYLSA53PQK4ZA%2F20240307%2Fus-east-1%2Fs3%2Faws4_request&X-Amz-Date=20240307T184851Z&X-Amz-Expires=300&X-Amz-Signature=0b56c7dc77cfb10e890157311cb17919fae9c0e72d50a3229788f645be9e5c63&X-Amz-SignedHeaders=host&actor_id=0&key_id=0&repo_id=23216272&response-content-disposition=attachment%3B filename%3DGit-2.44.0-64-bit.exe&response-content-type=application%2Foctet-stream"
  },
  {
    "name": "Windows NVM",
    "url": "https://objects.githubusercontent.com/github-production-release-asset-2e65be/24268127/88d77893-5385-48a8-a9b9-c0b138b118b9?X-Amz-Algorithm=AWS4-HMAC-SHA256&X-Amz-Credential=AKIAVCODYLSA53PQK4ZA%2F20240307%2Fus-east-1%2Fs3%2Faws4_request&X-Amz-Date=20240307T184957Z&X-Amz-Expires=300&X-Amz-Signature=e56cc3896b9e3b1111f3a7124a10c9794df7f786f820bf09f0ac02897a544250&X-Amz-SignedHeaders=host&actor_id=0&key_id=0&repo_id=24268127&response-content-disposition=attachment%3B filename%3Dnvm-setup.exe&response-content-type=application%2Foctet-stream"
  },
  {
    "name": "VS Code",
    "url": "https://vscode.download.prss.microsoft.com/dbazure/download/stable/1e790d77f81672c49be070e04474901747115651/VSCodeUserSetup-x64-1.87.1.exe"
  },
  {
    "name": "Virtualbox",
    "url": "https://download.virtualbox.org/virtualbox/7.0.14/VirtualBox-7.0.14-161095-Win.exe"
  },
  {
    "name": "Notion Calendar",
    "url": "https://dl.todesktop.com/210303leazlircz/windows/nsis/x64"
  }
]
